data_safe_haven/__init__.py
data_safe_haven/directories.py
data_safe_haven/singleton.py
data_safe_haven/version.py
data_safe_haven/administration/__init__.py
data_safe_haven/administration/users/__init__.py
data_safe_haven/administration/users/entra_users.py
data_safe_haven/administration/users/guacamole_users.py
data_safe_haven/administration/users/research_user.py
data_safe_haven/administration/users/user_handler.py
data_safe_haven/allowlist/__init__.py
data_safe_haven/allowlist/allowlist.py
data_safe_haven/commands/__init__.py
data_safe_haven/commands/allowlist.py
data_safe_haven/commands/cli.py
data_safe_haven/commands/config.py
data_safe_haven/commands/context.py
data_safe_haven/commands/pulumi.py
data_safe_haven/commands/shm.py
data_safe_haven/commands/sre.py
data_safe_haven/commands/users.py
data_safe_haven/config/__init__.py
data_safe_haven/config/config_sections.py
data_safe_haven/config/context.py
data_safe_haven/config/context_manager.py
data_safe_haven/config/dsh_pulumi_config.py
data_safe_haven/config/dsh_pulumi_project.py
data_safe_haven/config/shm_config.py
data_safe_haven/config/sre_config.py
data_safe_haven/console/__init__.py
data_safe_haven/console/format.py
data_safe_haven/console/pretty.py
data_safe_haven/console/prompts.py
data_safe_haven/exceptions/__init__.py
data_safe_haven/external/__init__.py
data_safe_haven/external/api/__init__.py
data_safe_haven/external/api/azure_sdk.py
data_safe_haven/external/api/credentials.py
data_safe_haven/external/api/graph_api.py
data_safe_haven/external/interface/__init__.py
data_safe_haven/external/interface/azure_container_instance.py
data_safe_haven/external/interface/azure_ipv4_range.py
data_safe_haven/external/interface/azure_postgresql_database.py
data_safe_haven/external/interface/pulumi_account.py
data_safe_haven/functions/__init__.py
data_safe_haven/functions/network.py
data_safe_haven/functions/strings.py
data_safe_haven/infrastructure/__init__.py
data_safe_haven/infrastructure/project_manager.py
data_safe_haven-5.7.0.dist-info/METADATA
data_safe_haven-5.7.0.dist-info/WHEEL
data_safe_haven-5.7.0.dist-info/entry_points.txt
data_safe_haven-5.7.0.dist-info/licenses/LICENSE
data_safe_haven-5.7.0.dist-info/RECORD
