Metadata-Version: 2.4
Name: data-safe-haven
Version: 5.7.0
Summary: An open-source framework for creating secure environments to analyse sensitive data.
Project-URL: Documentation, https://data-safe-haven.readthedocs.io
Project-URL: Issues, https://github.com/alan-turing-institute/data-safe-haven/issues
Project-URL: Source, https://github.com/alan-turing-institute/data-safe-haven
Author-email: Data Safe Haven development team <safehavendevs@turing.ac.uk>
License: BSD-3-Clause
License-File: LICENSE
Classifier: Development Status :: 5 - Production/Stable
Classifier: Environment :: Console
Classifier: Intended Audience :: Science/Research
Classifier: License :: OSI Approved :: BSD License
Classifier: Operating System :: OS Independent
Classifier: Programming Language :: Python :: 3
Classifier: Programming Language :: Python :: 3.12
Classifier: Topic :: Security
Classifier: Topic :: System :: Systems Administration
Requires-Python: ==3.12.*
Requires-Dist: appdirs==1.4.4
Requires-Dist: azure-core==1.38.0
Requires-Dist: azure-identity==1.25.1
Requires-Dist: azure-keyvault-certificates==4.10.0
Requires-Dist: azure-keyvault-keys==4.11.0
Requires-Dist: azure-keyvault-secrets==4.10.0
Requires-Dist: azure-mgmt-compute==37.1.0
Requires-Dist: azure-mgmt-containerinstance==10.1.0
Requires-Dist: azure-mgmt-dns==9.0.0
Requires-Dist: azure-mgmt-keyvault==13.0.0
Requires-Dist: azure-mgmt-msi==7.1.0
Requires-Dist: azure-mgmt-rdbms==10.1.1
Requires-Dist: azure-mgmt-resource==24.0.0
Requires-Dist: azure-mgmt-storage==24.0.0
Requires-Dist: azure-storage-blob==12.27.1
Requires-Dist: azure-storage-file-datalake==12.22.0
Requires-Dist: azure-storage-file-share==12.23.1
Requires-Dist: chevron==0.14.0
Requires-Dist: click==8.3.1
Requires-Dist: cryptography==46.0.3
Requires-Dist: fqdn==1.5.1
Requires-Dist: psycopg[binary]==3.1.19
Requires-Dist: pulumi-azure-native==3.12.0
Requires-Dist: pulumi-azuread==6.8.0
Requires-Dist: pulumi-random==4.18.5
Requires-Dist: pulumi==3.214.1
Requires-Dist: pydantic==2.12.5
Requires-Dist: pyjwt[crypto]==2.10.1
Requires-Dist: pytz==2025.2
Requires-Dist: pyyaml==6.0.3
Requires-Dist: rich==14.2.0
Requires-Dist: simple-acme-dns==4.0.0
Requires-Dist: typer==0.21.0
Requires-Dist: websocket-client==1.9.0
Provides-Extra: docs
Requires-Dist: emoji==2.15.0; extra == 'docs'
Requires-Dist: myst-parser==4.0.1; extra == 'docs'
Requires-Dist: pydata-sphinx-theme==0.16.1; extra == 'docs'
Requires-Dist: sphinx-togglebutton==0.3.2; extra == 'docs'
Requires-Dist: sphinx<10,>=7; extra == 'docs'
Requires-Dist: sphinxcontrib-typer==0.7.2; extra == 'docs'
Provides-Extra: lint
Requires-Dist: ansible-dev-tools==25.12.0; extra == 'lint'
Requires-Dist: ansible==13.2.0; extra == 'lint'
Requires-Dist: black==25.12.0; extra == 'lint'
Requires-Dist: mypy==1.19.1; extra == 'lint'
Requires-Dist: pandas-stubs==2.3.3.251219; extra == 'lint'
Requires-Dist: pydantic==2.12.5; extra == 'lint'
Requires-Dist: ruff==0.14.10; extra == 'lint'
Requires-Dist: types-appdirs==1.4.3.5; extra == 'lint'
Requires-Dist: types-chevron==0.14.2.20250103; extra == 'lint'
Requires-Dist: types-pytz==2025.2.0.20251108; extra == 'lint'
Requires-Dist: types-pyyaml==6.0.12.20250915; extra == 'lint'
Requires-Dist: types-requests==2.32.4.20250913; extra == 'lint'
Provides-Extra: test
Requires-Dist: coverage==7.13.1; extra == 'test'
Requires-Dist: freezegun==1.5.5; extra == 'test'
Requires-Dist: pytest-mock==3.15.1; extra == 'test'
Requires-Dist: pytest==9.0.2; extra == 'test'
Requires-Dist: requests-mock==1.12.1; extra == 'test'
